suitespotauth/__init__.py
suitespotauth/auth.py
suitespotauth/cli.py
suitespotauth/credentials.py
suitespotauth/exceptions.py
suitespotauth-0.3.5.dist-info/LICENSE
suitespotauth-0.3.5.dist-info/METADATA
suitespotauth-0.3.5.dist-info/WHEEL
suitespotauth-0.3.5.dist-info/entry_points.txt
suitespotauth-0.3.5.dist-info/top_level.txt
suitespotauth-0.3.5.dist-info/RECORD
