Metadata-Version: 2.1
Name: suitespotauth
Version: 0.3.5
Summary: Easy SuiteSpot authentication.
Author-email: Yakir Havin <y.havin@gmail.com>
Project-URL: Repository, https://github.com/yhavin/suitespotauth
Keywords: authentication,suitespot,property,management,capex,construction
Classifier: Programming Language :: Python :: 3
Classifier: License :: OSI Approved :: MIT License
Requires-Python: >=3.8
License-File: LICENSE
Requires-Dist: keyring
Requires-Dist: requests
Provides-Extra: aws
Requires-Dist: boto3 ; extra == 'aws'
Requires-Dist: botocore ; extra == 'aws'
Provides-Extra: azure
Requires-Dist: azure-identity ; extra == 'azure'
Requires-Dist: azure-keyvault ; extra == 'azure'
Provides-Extra: gcp
Requires-Dist: google-cloud-secret-manager ; extra == 'gcp'
Requires-Dist: google-api-core ; extra == 'gcp'
